CONTRIBUTING.rst
LICENSE
MANIFEST.in
README.rst
requirements.txt
setup.cfg
setup.py
django_migration_snapshots.egg-info/PKG-INFO
django_migration_snapshots.egg-info/SOURCES.txt
django_migration_snapshots.egg-info/dependency_links.txt
django_migration_snapshots.egg-info/not-zip-safe
django_migration_snapshots.egg-info/requires.txt
django_migration_snapshots.egg-info/top_level.txt
migration_snapshots/__init__.py
migration_snapshots/admin.py
migration_snapshots/apps.py
migration_snapshots/models.py
migration_snapshots/settings.py
migration_snapshots/utils.py
migration_snapshots/management/__init__.py
migration_snapshots/management/commands/__init__.py
migration_snapshots/management/commands/create_snapshot.py
migration_snapshots/migrations/0001_initial.py
migration_snapshots/migrations/__init__.py
migration_snapshots/tests/__init__.py
migration_snapshots/tests/test_visualizer.py