Metadata-Version: 2.1
Name: django-migration-snapshots
Version: 0.5.0
Summary: Capture django migration history snapshots
Home-page: https://github.com/Lenders-Cooperative/django-migration-snapshots
Author: Michael McClelland
Author-email: mmcclelland@thesummitgrp.com
License: BSD
Keywords: django-migration-snapshots
Classifier: Development Status :: 3 - Alpha
Classifier: Framework :: Django :: 1.11
Classifier: Framework :: Django :: 2.1
Classifier: Intended Audience :: Developers
Classifier: License :: OSI Approved :: BSD License
Classifier: Natural Language :: English
Classifier: Programming Language :: Python :: 2
Classifier: Programming Language :: Python :: 2.7
Classifier: Programming Language :: Python :: 3
Classifier: Programming Language :: Python :: 3.5
Classifier: Programming Language :: Python :: 3.6
License-File: LICENSE
